shared_camera/__init__.py
shared_camera/no_feed.jpg
neon_shared_camera-0.0.1a2.dist-info/LICENSE.md
neon_shared_camera-0.0.1a2.dist-info/METADATA
neon_shared_camera-0.0.1a2.dist-info/WHEEL
neon_shared_camera-0.0.1a2.dist-info/top_level.txt
neon_shared_camera-0.0.1a2.dist-info/RECORD
